moveread/sdk/__init__.py
moveread/sdk/api.py
moveread/sdk/games/__init__.py
moveread/sdk/games/api.py
moveread/sdk/games/ops/__init__.py
moveread/sdk/games/ops/annotate_.py
moveread/sdk/games/ops/create_.py
moveread/sdk/images/__init__.py
moveread/sdk/images/api.py
moveread/sdk/images/ops/__init__.py
moveread/sdk/images/ops/annotate_.py
moveread/sdk/images/ops/upsert_.py
moveread/sdk/players/__init__.py
moveread/sdk/players/api.py
moveread/sdk/players/ops/__init__.py
moveread/sdk/players/ops/annotate_.py
moveread/sdk/sheets/__init__.py
moveread/sdk/sheets/api.py
moveread/sdk/sheets/ops/__init__.py
moveread/sdk/sheets/ops/annotate_.py
moveread/sdk/util/__init__.py
moveread/sdk/util/blobs.py
moveread_sdk-0.1.3.dist-info/METADATA
moveread_sdk-0.1.3.dist-info/WHEEL
moveread_sdk-0.1.3.dist-info/top_level.txt
moveread_sdk-0.1.3.dist-info/RECORD
