Metadata-Version: 2.1
Name: moveread-sdk
Version: 0.1.3
Summary: Python SDK for the Moveread Core
Author-email: Marcel Claramunt <marcel@moveread.com>
Requires-Python: >=3.10
Requires-Dist: haskellian
Requires-Dist: moveread-core
Requires-Dist: moveread-errors
Requires-Dist: moveread-annotations
Provides-Extra: local
Requires-Dist: moveread-local ; extra == 'local'
